RTL/top.sv
//----------------
// Top Module
//----------------
module TOP
(
    input  logic CLK,
    input  logic RES,
    //
    input  logic [7:0] DIN,  // data input
    input  logic       LOAD, // data load
    input  logic       UP,   // count up
    input  logic       DN,   // count down
    //
    output logic [7:0] DOUT, // counter out
    output logic       OVF,  // over flow
    output logic       UDF   // under flow
);

//-----------------
// Internal Signals
//-----------------
logic [7:0] counter;
logic       counter_min;
logic       counter_max;

//--------------
// Data Output
//--------------
assign DOUT = counter; // 8bit data

//-----------------
// Main Counter
//-----------------
always_ff @(posedge CLK, posedge RES)
begin
    if (RES)
        counter <= 8'h00;
    else if (LOAD)
        counter <= DIN;
    else if (UP)
        counter <= counter + 8'h01;
    else if (DN)
        counter <= counter - 8'h01;
end

//----------------
// Overflow Pulse
//----------------
assign counter_max = (counter == 8'hff); 
//
always_ff @(posedge CLK, posedge RES)
begin
    if (RES)
        OVF <= 1'b0;
    else if (counter_max & UP)
        OVF <= 1'b1;
    else if (OVF)
        OVF <= 1'b0;
end    

//----------------
// Underflow Pulse
//----------------
assign counter_min = (counter == 8'h00); 
//
always_ff @(posedge CLK, posedge RES)
begin
    if (RES)
        UDF <= 1'b0;
    else if (counter_min & DN)
        UDF <= 1'b1;
    else if (UDF)
        UDF <= 1'b0;
end    

endmodule

SIM/tb.sv
`timescale 1ns/100ps 

`define TB_CYCLE  20          //ns 
`define TB_FINISH_COUNT 10000 //cyc 

//------------------
// Top of Test Bench 
//------------------ 
module tb();

//----------------------------- 
// Generate Wave File to Check 
//----------------------------- 
initial 
begin    
    $dumpfile("tb.vcd");        
    $dumpvars(0, tb); 
end 

//------------------------------- 
// Generate Clock 
//------------------------------- 
logic clk; 
// 
initial clk = 1'b0; 
always #(`TB_CYCLE / 2) clk = ~clk; 

//-------------------------- 
// Generate Reset 
//-------------------------- 
logic res;
//
initial
begin
    res = 1'b1;
        # (`TB_CYCLE * 10)
    res = 1'b0;	 
end 

//---------------------- 
// Cycle Counter 
//---------------------- 
logic [31:0] tb_cycle_counter; 
// 
always_ff @(posedge clk, posedge res) 
begin    
    if (res)        
        tb_cycle_counter <= 32'h0;    
    else        
        tb_cycle_counter <= tb_cycle_counter + 32'h1; 
end 
//
initial
begin
    forever
    begin
        @(posedge clk);
        if (tb_cycle_counter == `TB_FINISH_COUNT)
        begin
            $display("***** SIMULATION TIMEOUT ***** at %d", tb_cycle_counter);
            $finish;
        end
    end
end

//-----------------------
// Module Under Test
//-----------------------
logic [7:0] din;
logic       load;
logic       up, dn;
logic [7:0] dout;
logic       ovf;
logic       udf;
//
TOP u_TOP
(
    .CLK   (clk),
    .RES   (res),
    //
    .DIN   (din ),   // data input
    .LOAD  (load),   // data load
    .UP    (up  ),   // count up
    .DN    (dn  ),   // count down
    //
    .DOUT  (dout),   // counter output
    .OVF   (ovf ),   // over flow
    .UDF   (udf )    // under flow
);

//-----------------
// Task: Initialize
//-----------------
task TASK_INIT();
begin
    #(`TB_CYCLE *  0);
    din  = 8'hxx;
    load = 1'b0;
    up   = 1'b0;    
    dn   = 1'b0;    
    //
    #(`TB_CYCLE *  12);
end
endtask

//----------------
// Task: Load Data
//----------------
task TASK_LOAD(input logic [7:0] data);
begin
    #(`TB_CYCLE *  0);
    din = data;
    load = 1'b1;
    //
    #(`TB_CYCLE *  1);
    din  = 8'hxx;  
    load = 1'b0;
end
endtask

//----------------
// Task: Up Count
//----------------
task TASK_UP();
begin
    #(`TB_CYCLE *  0);
    up = 1'b1;
    //
    #(`TB_CYCLE *  1);
    up = 1'b0;    
end
endtask

//------------------
// Task: Down Count
//------------------
task TASK_DOWN();
begin
    #(`TB_CYCLE *  0);
    dn = 1'b1;
    //
    #(`TB_CYCLE *  1);
    dn = 1'b0;    
end
endtask

//-----------------------
// Task: Any Combination
//-----------------------
task TASK_ANY
(
    input logic [7:0] i, // data input
    input logic       l, // data load
    input logic       u, // count up
    input logic       d  // count down
);
begin
    #(`TB_CYCLE *  0);
    din  = i;
    load = l;
    up   = u;
    dn   = d;
    //
    #(`TB_CYCLE *  1);
    din  = 8'hxx;
    load = 1'b0;
    up   = 1'b0;
    dn   = 1'b0;
end
endtask

//---------------------
// Test Pattern
//---------------------
initial
begin
    TASK_INIT();
    
    // Test Load Function
    TASK_LOAD(8'h01);
    TASK_LOAD(8'h23);
    TASK_LOAD(8'h45);
    TASK_LOAD(8'h67);
    
    // Test Up/Down
    TASK_LOAD(8'h00);
    TASK_UP  ();
    TASK_UP  ();
    TASK_UP  ();
    TASK_UP  ();
    TASK_DOWN();    
    TASK_DOWN();
    
    // Test Overflow/Underflow
    TASK_LOAD(8'hfe);
    TASK_UP  ();
    TASK_UP  ();
    TASK_UP  ();
    TASK_UP  ();
    TASK_DOWN();    
    TASK_DOWN();
    TASK_DOWN();    
    TASK_DOWN();
    
    // Test Conflict
    TASK_ANY(8'h12, 1'b1, 1'b1, 1'b1); // load
    TASK_ANY(8'h34, 1'b1, 1'b0, 1'b1); // load
    TASK_ANY(8'h56, 1'b1, 1'b1, 1'b0); // load
    TASK_ANY(8'h78, 1'b0, 1'b1, 1'b1); // up
    TASK_ANY(8'h9a, 1'b0, 1'b0, 1'b1); // down

    // End of Simulation
    #(`TB_CYCLE * 20);
    $finish; 
end

endmodule

SIM/tb.vcd
$date
	Thu Feb 12 22:58:22 2026
$end
$version
	Icarus Verilog
$end
$timescale
	100ps
$end
$scope module tb $end
$var wire 1 ! udf $end
$var wire 1 " ovf $end
$var wire 8 # dout [7:0] $end
$var reg 1 $ clk $end
$var reg 8 % din [7:0] $end
$var reg 1 & dn $end
$var reg 1 ' load $end
$var reg 1 ( res $end
$var reg 32 ) tb_cycle_counter [31:0] $end
$var reg 1 * up $end
$scope module u_TOP $end
$var wire 1 $ CLK $end
$var wire 8 + DIN [7:0] $end
$var wire 1 & DN $end
$var wire 8 , DOUT [7:0] $end
$var wire 1 ' LOAD $end
$var wire 1 ( RES $end
$var wire 1 * UP $end
$var wire 1 - counter_min $end
$var wire 1 . counter_max $end
$var reg 1 " OVF $end
$var reg 1 ! UDF $end
$var reg 8 / counter [7:0] $end
$upscope $end
$scope task TASK_ANY $end
$var reg 1 0 d $end
$var reg 8 1 i [7:0] $end
$var reg 1 2 l $end
$var reg 1 3 u $end
$upscope $end
$scope task TASK_DOWN $end
$upscope $end
$scope task TASK_INIT $end
$upscope $end
$scope task TASK_LOAD $end
$var reg 8 4 data [7:0] $end
$upscope $end
$scope task TASK_UP $end
$upscope $end
$upscope $end
$enddefinitions $end
$comment Show the parameter values. $end
$dumpall
$end
#0
$dumpvars
bx 4
x3
x2
bx 1
x0
b0 /
0.
1-
b0 ,
bx +
0*
bx )
1(
0'
0&
bx %
0$
b0 #
0"
0!
$end
#100
b0 )
1$
#200
0$
#300
1$
#400
0$
#500
1$
#600
0$
#700
1$
#800
0$
#900
1$
#1000
0$
#1100
1$
#1200
0$
#1300
1$
#1400
0$
#1500
1$
#1600
0$
#1700
1$
#1800
0$
#1900
1$
#2000
0$
0(
#2100
b1 )
1$
#2200
0$
#2300
b10 )
1$
#2400
1'
b1 %
b1 +
0$
b1 4
#2500
b11 )
0-
b1 #
b1 ,
b1 /
1$
#2600
0$
b100011 4
1'
b100011 %
b100011 +
#2700
b100011 #
b100011 ,
b100011 /
b100 )
1$
#2800
0$
b1000101 4
1'
b1000101 %
b1000101 +
#2900
b101 )
b1000101 #
b1000101 ,
b1000101 /
1$
#3000
0$
b1100111 4
1'
b1100111 %
b1100111 +
#3100
b1100111 #
b1100111 ,
b1100111 /
b110 )
1$
#3200
0$
b0 4
1'
b0 %
b0 +
#3300
b111 )
1-
b0 #
b0 ,
b0 /
1$
#3400
1*
0$
0'
bx %
bx +
#3500
0-
b1 #
b1 ,
b1 /
b1000 )
1$
#3600
0$
1*
#3700
b1001 )
b10 #
b10 ,
b10 /
1$
#3800
0$
1*
#3900
b11 #
b11 ,
b11 /
b1010 )
1$
#4000
0$
1*
#4100
b1011 )
b100 #
b100 ,
b100 /
1$
#4200
1&
0$
0*
#4300
b11 #
b11 ,
b11 /
b1100 )
1$
#4400
0$
1&
#4500
b1101 )
b10 #
b10 ,
b10 /
1$
#4600
1'
b11111110 %
b11111110 +
0$
b11111110 4
0&
#4700
b11111110 #
b11111110 ,
b11111110 /
b1110 )
1$
#4800
1*
0$
0'
bx %
bx +
#4900
b1111 )
1.
b11111111 #
b11111111 ,
b11111111 /
1$
#5000
0$
1*
#5100
0.
1-
b0 #
b0 ,
b0 /
1"
b10000 )
1$
#5200
0$
1*
#5300
b10001 )
0"
0-
b1 #
b1 ,
b1 /
1$
#5400
0$
1*
#5500
b10 #
b10 ,
b10 /
b10010 )
1$
#5600
1&
0$
0*
#5700
b10011 )
b1 #
b1 ,
b1 /
1$
#5800
0$
1&
#5900
1-
b0 #
b0 ,
b0 /
b10100 )
1$
#6000
0$
1&
#6100
b10101 )
1!
1.
0-
b11111111 #
b11111111 ,
b11111111 /
1$
#6200
0$
1&
#6300
0.
b11111110 #
b11111110 ,
b11111110 /
0!
b10110 )
1$
#6400
1*
1'
b10010 %
b10010 +
0$
10
13
12
b10010 1
1&
#6500
b10111 )
b10010 #
b10010 ,
b10010 /
1$
#6600
0$
03
b110100 1
1&
0*
1'
b110100 %
b110100 +
#6700
b110100 #
b110100 ,
b110100 /
b11000 )
1$
#6800
1*
0$
00
13
b1010110 1
0&
1'
b1010110 %
b1010110 +
#6900
b11001 )
b1010110 #
b1010110 ,
b1010110 /
1$
#7000
1&
0$
10
02
b1111000 1
1*
0'
b1111000 %
b1111000 +
#7100
b1010111 #
b1010111 ,
b1010111 /
b11010 )
1$
#7200
0$
03
b10011010 1
1&
0*
b10011010 %
b10011010 +
#7300
b11011 )
b1010110 #
b1010110 ,
b1010110 /
1$
#7400
0$
0&
bx %
bx +
#7500
b11100 )
1$
#7600
0$
#7700
b11101 )
1$
#7800
0$
#7900
b11110 )
1$
#8000
0$
#8100
b11111 )
1$
#8200
0$
#8300
b100000 )
1$
#8400
0$
#8500
b100001 )
1$
#8600
0$
#8700
b100010 )
1$
#8800
0$
#8900
b100011 )
1$
#9000
0$
#9100
b100100 )
1$
#9200
0$
#9300
b100101 )
1$
#9400
0$
#9500
b100110 )
1$
#9600
0$
#9700
b100111 )
1$
#9800
0$
#9900
b101000 )
1$
#10000
0$
#10100
b101001 )
1$
#10200
0$
#10300
b101010 )
1$
#10400
0$
#10500
b101011 )
1$
#10600
0$
#10700
b101100 )
1$
#10800
0$
#10900
b101101 )
1$
#11000
0$
#11100
b101110 )
1$
#11200
0$
#11300
b101111 )
1$
